PyCSVDataCleaner/PyCSVDataCleaner.py
PyCSVDataCleaner/__init__.py
PyCSVDataCleaner-0.1.1.dist-info/License
PyCSVDataCleaner-0.1.1.dist-info/METADATA
PyCSVDataCleaner-0.1.1.dist-info/WHEEL
PyCSVDataCleaner-0.1.1.dist-info/top_level.txt
PyCSVDataCleaner-0.1.1.dist-info/RECORD
