Metadata-Version: 2.1
Name: PyCSVDataCleaner
Version: 0.1.1
Summary: A lightweight Python package to clean CSV files
Author: Md. Ismiel Hossen Abir
Author-email: ismielabir1971@gmail.com
Classifier: Programming Language :: Python :: 3
Classifier: License :: OSI Approved :: MIT License
Classifier: Operating System :: OS Independent
Requires-Python: >=3.6
License-File: License
